networkx_reverse_topological_sort.py
networkx_reverse_topological_sort-0.1.0a0.dist-info/licenses/LICENSE
networkx_reverse_topological_sort-0.1.0a0.dist-info/METADATA
networkx_reverse_topological_sort-0.1.0a0.dist-info/WHEEL
networkx_reverse_topological_sort-0.1.0a0.dist-info/top_level.txt
networkx_reverse_topological_sort-0.1.0a0.dist-info/RECORD
