Metadata-Version: 2.4
Name: networkx-reverse-topological-sort
Version: 0.1.0a0
Summary: Reverse topological sort utilities for NetworkX: easily stratify or sort nodes in a DAG from leaves to root.
Author-email: Jifeng Wu <jifengwu2k@gmail.com>
License-Expression: MIT
Project-URL: Homepage, https://github.com/jifengwu2k/networkx-reverse-topological-sort
Project-URL: Bug Tracker, https://github.com/jifengwu2k/networkx-reverse-topological-sort/issues
Classifier: Programming Language :: Python :: 2
Classifier: Programming Language :: Python :: 3
Classifier: Operating System :: OS Independent
Requires-Python: >=2
License-File: LICENSE
Requires-Dist: networkx
Dynamic: license-file
